main.py
data/__init__.py
data/run_button.png
data/synth_button.png
utils/__init__.py
utils/auto_run.py
utils/common.py
EbSynth_Auto_Runer-0.0.1.dist-info/LICENSE
EbSynth_Auto_Runer-0.0.1.dist-info/METADATA
EbSynth_Auto_Runer-0.0.1.dist-info/WHEEL
EbSynth_Auto_Runer-0.0.1.dist-info/entry_points.txt
EbSynth_Auto_Runer-0.0.1.dist-info/top_level.txt
EbSynth_Auto_Runer-0.0.1.dist-info/RECORD
