Metadata-Version: 2.1
Name: EbSynth-Auto-Runer
Version: 0.0.1
Summary: Support Mac for fully automated running of EbSynth(.ebs).
Home-page: https://github.com/Littleor/ebsynth-auto-runer
Author: Littleor
Author-email: me@littleor.cn
License: Apache License 2.0
Classifier: Programming Language :: Python
Classifier: Programming Language :: Python :: 3
Classifier: Programming Language :: Python :: 3.6
Classifier: Programming Language :: Python :: Implementation :: CPython
Classifier: Programming Language :: Python :: Implementation :: PyPy
Classifier: License :: OSI Approved :: Apache Software License
License-File: LICENSE
Requires-Dist: opencv-python >=4.8.1.78
Requires-Dist: PyAutoGUI >=0.9.54
Requires-Dist: rich >=13.7.0
Requires-Dist: tqdm >=4.66.1
